{
  "alignment": "start",
  "animateLoading": false,
  "backgroundColor": "white",
  "borderColor": "#E0DEDE",
  "borderRadius": "{{appsmith.theme.borderRadius.appBorderRadius}}",
  "borderWidth": "1",
  "bottomRow": 11.200000000000001,
  "boxShadow": "{{appsmith.theme.boxShadow.appBoxShadow}}",
  "children": [
    {
      "borderRadius": "{{appsmith.theme.borderRadius.appBorderRadius}}",
      "bottomRow": 112.00000000000001,
      "boxShadow": "{{appsmith.theme.boxShadow.appBoxShadow}}",
      "canExtend": false,
      "containerStyle": "none",
      "detachFromLayout": true,
      "dynamicBindingPathList": [
        {
          "key": "borderRadius"
        },
        {
          "key": "boxShadow"
        }
      ],
      "dynamicHeight": "AUTO_HEIGHT",
      "flexLayers": [
        {
          "children": [
            {
              "align": "start",
              "id": "1nihwmwpbk"
            }
          ]
        },
        {
          "children": [
            {
              "align": "start",
              "id": "54llfc056u"
            },
            {
              "align": "end",
              "id": "i01ezq5mw2"
            }
          ]
        }
      ],
      "isLoading": false,
      "isVisible": true,
      "key": "310uxcek5q",
      "layout": [
        {
          "layout": [
            {
              "isDropTarget": true,
              "isPermanent": true,
              "layout": [
                {
                  "layout": [
                    {
                      "alignment": "start",
                      "widgetId": "1nihwmwpbk",
                      "widgetType": "TEXT_WIDGET"
                    }
                  ],
                  "layoutId": "0ipgwc6j4e",
                  "layoutStyle": {
                    "alignSelf": "stretch"
                  },
                  "layoutType": "WIDGET_ROW"
                },
                {
                  "layout": [
                    {
                      "alignment": "start",
                      "widgetId": "54llfc056u",
                      "widgetType": "TEXT_WIDGET"
                    }
                  ],
                  "layoutId": "hu577rcnkn",
                  "layoutStyle": {
                    "alignSelf": "stretch"
                  },
                  "layoutType": "WIDGET_ROW"
                },
                {
                  "layout": [
                    {
                      "alignment": "start",
                      "widgetId": "p69mfvzqeq",
                      "widgetType": "TEXT_WIDGET"
                    }
                  ],
                  "layoutId": "hfvlmuquo6",
                  "layoutStyle": {
                    "alignSelf": "stretch"
                  },
                  "layoutType": "WIDGET_ROW"
                }
              ],
              "layoutId": "o54hd2h3tv",
              "layoutStyle": {
                "flexGrow": 1
              },
              "layoutType": "LAYOUT_COLUMN"
            },
            {
              "isDropTarget": true,
              "isPermanent": true,
              "layout": [
                {
                  "alignment": "start",
                  "widgetId": "i01ezq5mw2",
                  "widgetType": "IMAGE_WIDGET"
                }
              ],
              "layoutId": "0kunxrgzkx",
              "layoutStyle": {
                "alignSelf": "flex-end"
              },
              "layoutType": "WIDGET_COLUMN"
            }
          ],
          "layoutId": "05c7ykmivh",
          "layoutStyle": {
            "wrap": "wrap-reverse"
          },
          "layoutType": "LAYOUT_ROW"
        }
      ],
      "leftColumn": 0,
      "maxDynamicHeight": 9000,
      "minDynamicHeight": 4,
      "minHeight": 140,
      "minWidth": 450,
      "mobileBottomRow": 156.00000000000006,
      "mobileLeftColumn": 0,
      "mobileRightColumn": 64,
      "mobileTopRow": 0,
      "needsErrorInfo": false,
      "parentColumnSpace": 1,
      "parentId": "c1wxrsssgp",
      "parentRowSpace": 1,
      "positioning": "vertical",
      "renderMode": "CANVAS",
      "responsiveBehavior": "fill",
      "rightColumn": 64,
      "topRow": 0,
      "type": "CANVAS_WIDGET",
      "useAutoLayout": true,
      "version": 1,
      "widgetId": "wzeukyjwdj",
      "widgetName": "Canvas4"
    }
  ],
  "dynamicBindingPathList": [
    {
      "key": "borderRadius"
    },
    {
      "key": "boxShadow"
    }
  ],
  "dynamicHeight": "AUTO_HEIGHT",
  "dynamicTriggerPathList": [],
  "flexVerticalAlignment": "stretch",
  "isCanvas": true,
  "isLoading": false,
  "isVisible": true,
  "key": "jtcz07345c",
  "leftColumn": 117.89473684210526,
  "maxDynamicHeight": 9000,
  "minDynamicHeight": 10,
  "mobileBottomRow": 64.80000000000003,
  "mobileLeftColumn": 0,
  "mobileRightColumn": 64,
  "mobileTopRow": 49.20000000000002,
  "needsErrorInfo": false,
  "parentColumnSpace": 18.125,
  "parentId": "3bxmrjlup1",
  "parentRowSpace": 10,
  "positioning": "fixed",
  "renderMode": "CANVAS",
  "responsiveBehavior": "fill",
  "rightColumn": 157.19298245614036,
  "shouldScrollContents": true,
  "topRow": 0,
  "type": "STATBOX_WIDGET",
  "widgetId": "c1wxrsssgp",
  "widgetName": "Statbox3"
}