{
  "gitSyncId": "66d54fc7ce77550208296c31_5a13d2bb-22ca-4e2c-8ad2-a18ed9b74083",
  "id": "Requesters_V2_requesters_reset_button.myFun2",
  "pluginId": "js-plugin",
  "pluginType": "JS",
  "unpublishedAction": {
    "actionConfiguration": {
      "encodeParamsToggle": true,
      "jsArguments": [],
      "paginationType": "NONE",
      "timeoutInMillisecond": 10000
    },
    "clientSideExecution": true,
    "collectionId": "Requesters_V2_requesters_reset_button",
    "confirmBeforeExecute": false,
    "datasource": {
      "isAutoGenerated": false,
      "name": "UNUSED_DATASOURCE",
      "pluginId": "js-plugin"
    },
    "dynamicBindingPathList": [
      {
        "key": "body"
      }
    ],
    "executeOnLoad": false,
    "fullyQualifiedName": "requesters_reset_button.myFun2",
    "name": "myFun2",
    "pageId": "Requesters_V2",
    "userSetOnLoad": false
  }
}